questo/__init__.py
questo/abstract/__init__.py
questo/abstract/abstract_element.py
questo/internals.py
questo/prompt/__init__.py
questo/prompt/key_handler.py
questo/prompt/prompt.py
questo/prompt/renderer.py
questo/prompt/state.py
questo/select/__init__.py
questo/select/key_handler.py
questo/select/renderer.py
questo/select/select.py
questo/select/state.py
questo-0.4.1.dist-info/LICENSE
questo-0.4.1.dist-info/METADATA
questo-0.4.1.dist-info/WHEEL
questo-0.4.1.dist-info/RECORD
