Metadata-Version: 2.3
Name: questo
Version: 0.4.1
Summary: A library of extensible and modular CLI prompt elements
License: MIT
Keywords: python
Author: Peter Vyboch
Author-email: pvyboch1@gmail.com
Requires-Python: >=3.7.8,<4.0.0
Classifier: License :: OSI Approved :: MIT License
Classifier: Programming Language :: Python :: 3
Classifier: Programming Language :: Python :: 3.8
Classifier: Programming Language :: Python :: 3.9
Classifier: Programming Language :: Python :: 3.10
Classifier: Programming Language :: Python :: 3.11
Classifier: Programming Language :: Python :: 3.12
Classifier: Programming Language :: Python :: 3.13
Requires-Dist: python-yakh (>=0.4.1,<0.5.0)
Requires-Dist: rich (>=12.2.0)
Project-URL: Repository, https://github.com/petereon/questo
